ChangeLog
README.md
requirements.sh
requirements.txt
setup.cfg
setup.py
observatory/platform/__init__.py
observatory/platform/config-terraform.yaml.jinja2
observatory/platform/config.yaml.jinja2
observatory/platform/observatory_config.py
observatory/platform/cli/__init__.py
observatory/platform/cli/cli.py
observatory/platform/cli/cli_utils.py
observatory/platform/cli/generate_command.py
observatory/platform/cli/platform_command.py
observatory/platform/cli/terraform_command.py
observatory/platform/cli/templates/__init__.py
observatory/platform/cli/templates/generate_project/__init__.py
observatory/platform/cli/templates/generate_project/generate_schema_csv.py
observatory/platform/cli/templates/generate_project/test_generate_schema_csv.py
observatory/platform/dags/__init__.py
observatory/platform/dags/dummy_telescope.py
observatory/platform/dags/load_dags.py
observatory/platform/dags/vm_create.py
observatory/platform/dags/vm_destroy.py
observatory/platform/docker/Dockerfile.apiserver.jinja2
observatory/platform/docker/Dockerfile.observatory.jinja2
observatory/platform/docker/Dockerfile.package_install.jinja2
observatory/platform/docker/Dockerfile.seed_db.jinja2
observatory/platform/docker/__init__.py
observatory/platform/docker/builder.py
observatory/platform/docker/compose_runner.py
observatory/platform/docker/docker-compose.observatory.yml.jinja2
observatory/platform/docker/entrypoint-airflow.sh.jinja2
observatory/platform/docker/entrypoint-api.sh.jinja2
observatory/platform/docker/entrypoint-root.sh
observatory/platform/docker/platform_runner.py
observatory/platform/docker/seed_db.sh.jinja2
observatory/platform/elastic/__init__.py
observatory/platform/elastic/docker-compose.yml.jinja2
observatory/platform/elastic/elastic.py
observatory/platform/elastic/elastic_environment.py
observatory/platform/elastic/kibana.py
observatory/platform/terraform/__init__.py
observatory/platform/terraform/build.sh
observatory/platform/terraform/main.tf
observatory_platform.egg-info/PKG-INFO
observatory_platform.egg-info/SOURCES.txt
observatory_platform.egg-info/dependency_links.txt
observatory_platform.egg-info/entry_points.txt
observatory_platform.egg-info/not-zip-safe
observatory_platform.egg-info/pbr.json
observatory_platform.egg-info/requires.txt
observatory_platform.egg-info/top_level.txt