Metadata-Version: 2.1
Name: observatory-platform
Version: 0.5.0
Summary: The Observatory Platform is an environment for fetching, processing and analysing data to understand how well universities operate as Open Knowledge Institutions.
Home-page: https://github.com/The-Academic-Observatory/observatory-platform
Author: Curtin University
Author-email: agent@observatory.academy
License: Apache License Version 2.0
Project-URL: Bug Tracker, https://github.com/The-Academic-Observatory/observatory-platform/issues
Project-URL: Documentation, https://observatory-platform.readthedocs.io/en/latest/
Project-URL: Source Code, https://github.com/The-Academic-Observatory/observatory-platform
Keywords: science,data,workflows,academic institutes,observatory-platform
Platform: UNKNOWN
Classifier: Development Status :: 2 - Pre-Alpha
Classifier: Environment :: Console
Classifier: Environment :: Web Environment
Classifier: Intended Audience :: Developers
Classifier: Intended Audience :: Science/Research
Classifier: License :: OSI Approved :: Apache Software License
Classifier: Operating System :: OS Independent
Classifier: Programming Language :: Python :: 3 :: Only
Classifier: Programming Language :: Python :: 3
Classifier: Programming Language :: Python :: 3.7
Classifier: Programming Language :: Python :: 3.8
Classifier: Topic :: Scientific/Engineering
Classifier: Topic :: Software Development :: Libraries
Classifier: Topic :: Software Development :: Libraries :: Python Modules
Classifier: Topic :: Utilities
Requires-Python: >=3.7
Provides-Extra: tests
